assistant/__init__.py
assistant/__main__.py
assistant/cli.py
assistant/input_utils.py
assistant/ui_utils.py
assistant/core/config.py
assistant/debug/tty_probe.py
assistant/tools/__init__.py
assistant/tools/ask.py
assistant/tools/file_creator.py
assistant/tools/file_modifier.py
assistant/tools/perplexity.py
assistant/tools/terminal_executor.py
assistant/utils/summarizer.py
iwasborninbali-0.1.5.dist-info/METADATA
iwasborninbali-0.1.5.dist-info/WHEEL
iwasborninbali-0.1.5.dist-info/entry_points.txt
iwasborninbali-0.1.5.dist-info/top_level.txt
iwasborninbali-0.1.5.dist-info/RECORD
