Metadata-Version: 2.4
Name: iwasborninbali
Version: 0.1.5
Summary: AI Assistant for software development tasks, guided by o3.
Author-email: Platform AI <iwasborninbali@platformai.solutions>
Project-URL: Homepage, https://github.com/platform-ai/assistant
Project-URL: Bug Tracker, https://github.com/platform-ai/assistant/issues
Classifier: Programming Language :: Python :: 3
Classifier: License :: OSI Approved :: MIT License
Classifier: Operating System :: OS Independent
Requires-Python: >=3.10
Requires-Dist: openai>=1.3.0
Requires-Dist: requests>=2.20.0
Requires-Dist: google-generativeai>=0.4.0
Requires-Dist: click>=8
Requires-Dist: python-dotenv>=1.0
Provides-Extra: ui
Requires-Dist: rich>=13; extra == "ui"
Requires-Dist: prompt_toolkit>=3.0; extra == "ui"
Provides-Extra: dev
Requires-Dist: pytest>=7.4; extra == "dev"
